add_signif/__init__.py
add_signif/core.py
add_signif-0.1.0.dist-info/licenses/LICENSE
add_signif-0.1.0.dist-info/METADATA
add_signif-0.1.0.dist-info/WHEEL
add_signif-0.1.0.dist-info/top_level.txt
add_signif-0.1.0.dist-info/RECORD
