Metadata-Version: 2.4
Name: add_signif
Version: 0.1.0
Summary: Add significance bars to a plot.
Author-email: Devin Austin <devinaustinb@gmail.com>
License: MIT
Requires-Python: >=3.10
License-File: LICENSE
Requires-Dist: matplotlib
Dynamic: license-file
